pygada_runtime/__init__.py
pygada_runtime/__version__.py
pygada_runtime/_cache.py
pygada_runtime/datadir.py
pygada_runtime/node.py
pygada_runtime/program.py
pygada_runtime/typing.py
pygada_runtime/parser/__init__.py
pygada_runtime/parser/dist/GadaLexer.py
pygada_runtime/parser/dist/GadaListener.py
pygada_runtime/parser/dist/GadaParser.py
pygada_runtime/parser/dist/GadaVisitor.py
pygada_runtime/parser/dist/__init__.py
test/foo/__init__.py
test/foo/bar/__init__.py
pygada_runtime-0.5.1a0.dist-info/LICENSE
pygada_runtime-0.5.1a0.dist-info/METADATA
pygada_runtime-0.5.1a0.dist-info/WHEEL
pygada_runtime-0.5.1a0.dist-info/top_level.txt
pygada_runtime-0.5.1a0.dist-info/RECORD
