Metadata-Version: 2.1
Name: pygada-runtime
Version: 0.5.1a0
Summary: Python runtime for gada nodes
Home-page: https://github.com/gadalang/pygada-runtime
Author: Jeremy Morosi
Author-email: jeremymorosi@hotmail.com
License: UNKNOWN
Project-URL: Bug Tracker, https://github.com/gadalang/pygada-runtime/issues
Project-URL: Source Code, https://github.com/gadalang/pygada-runtime/
Platform: UNKNOWN
Classifier: Development Status :: 3 - Alpha
Classifier: Intended Audience :: Developers
Classifier: Topic :: Software Development :: Build Tools
Classifier: Programming Language :: Python :: 3.8
Classifier: Programming Language :: Python :: 3.9
Requires-Python: >=3.8
Requires-Dist: pyyaml
Requires-Dist: antlr4-python3-runtime (==4.10)
